log_analysis_tool/__init__.py
log_analysis_tool/app.py
log_analysis_tool/logo.py
log_analysis_tool/ui.py
log_analysis_tool-1.0.0.dist-info/METADATA
log_analysis_tool-1.0.0.dist-info/WHEEL
log_analysis_tool-1.0.0.dist-info/entry_points.txt
log_analysis_tool-1.0.0.dist-info/top_level.txt
log_analysis_tool-1.0.0.dist-info/RECORD
