Metadata-Version: 2.1
Name: log-analysis-tool
Version: 1.0.0
Summary: log analysis tool
Author: gwt
Author-email: 1973735972@qq.com
License: UNKNOWN
Keywords: Log,screen,application,PyQt5,Python 3
Platform: UNKNOWN
Requires-Python: >=3.6
Requires-Dist: pyqt5
Requires-Dist: easydict
Requires-Dist: openpyxl
